chromakit/__init__.py
chromakit/base.py
chromakit/modify.py
chromakit/presets.py
chromakit/printkit.py
chromakit-0.0.4.dist-info/licenses/LICENCE
chromakit-0.0.4.dist-info/METADATA
chromakit-0.0.4.dist-info/WHEEL
chromakit-0.0.4.dist-info/top_level.txt
chromakit-0.0.4.dist-info/RECORD
