Metadata-Version: 2.4
Name: chromakit
Version: 0.0.4
Summary: My first module for colors
Home-page: https://github.com/MatthewKim12/chromakit
Author: MatthewKim
Author-email: kimdjn12@gmail.com
Project-URL: Bug Tracker, https://github.com/MatthewKim12/chromakit/issues
Project-URL: Source Code, https://github.com/MatthewKim12/chromakit-code
Classifier: Programming Language :: Python :: 3
Classifier: License :: OSI Approved :: MIT License
Classifier: Operating System :: OS Independent
License-File: LICENCE
Requires-Dist: colorama>=0.4.6
Dynamic: license-file
